jsonschemata/__init__.py
jsonschemata/edit.py
jsonschemata/registry.py
jsonschemata/_data/array/unique-strings.yaml
jsonschemata/_data/color/css-name.yaml
jsonschemata/_data/color/css.yaml
jsonschemata/_data/color/hex-string.yaml
jsonschemata/_data/color/hsl-array.yaml
jsonschemata/_data/color/hsl-string.yaml
jsonschemata/_data/color/hsla-array.yaml
jsonschemata/_data/color/rgb-array.yaml
jsonschemata/_data/color/rgb-string.yaml
jsonschemata/_data/color/rgba-array.yaml
jsonschemata/_data/config/pydata-sphinx-theme.yaml
jsonschemata/_data/config/setuptools.yaml
jsonschemata/_data/config/sphinx.yaml
jsonschemata/_data/config/versioningit.yaml
jsonschemata/_data/config/github/funding.yaml
jsonschemata/_data/config/github/form/body.yaml
jsonschemata/_data/config/github/label/description.yaml
jsonschemata/_data/config/python/pyproject-entrypoint.yaml
jsonschemata/_data/config/python/pyproject-person.yaml
jsonschemata/_data/config/python/pyproject.yaml
jsonschemata/_data/date/yyyy-mm-dd.yaml
jsonschemata/_data/id/doi.yaml
jsonschemata/_data/id/email.yaml
jsonschemata/_data/id/linkedin.yaml
jsonschemata/_data/id/orcid.yaml
jsonschemata/_data/id/researchgate.yaml
jsonschemata/_data/id/spdx-license.yaml
jsonschemata/_data/id/twitter.yaml
jsonschemata/_data/id/github/node.yaml
jsonschemata/_data/id/github/rest.yaml
jsonschemata/_data/id/github/user.yaml
jsonschemata/_data/integer/non-negative.yaml
jsonschemata/_data/number/non-negative.yaml
jsonschemata/_data/path/dir-name.yaml
jsonschemata/_data/path/posix/absolute-from-cwd.yaml
jsonschemata/_data/string/nonempty.yaml
jsonschemata/_data/string/oneline.yaml
jsonschemata/_data/uri/mailto.yaml
jsonschemata/_data/url/README.md
jsonschemata/_data/url/ftp.yaml
jsonschemata/_data/url/http-explicit.yaml
jsonschemata/_data/url/http-ftp-sftp.yaml
jsonschemata/_data/url/http-implicit.yaml
jsonschemata/_data/url/https.yaml
jsonschemata/_data/url/sftp.yaml
jsonschemata/_data/url/github/user.yaml
jsonschemata-0.1.0.dist-info/METADATA
jsonschemata-0.1.0.dist-info/WHEEL
jsonschemata-0.1.0.dist-info/top_level.txt
jsonschemata-0.1.0.dist-info/RECORD
