Metadata-Version: 2.2
Name: JSONSchemata
Version: 0.1.0
Requires-Python: >=3.10
Requires-Dist: referencing<0.37,>=0.35
Requires-Dist: PkgData<0.2,>=0.1
Requires-Dist: PySerials<0.2,>=0.1
Requires-Dist: PyLinks<0.2,>=0.1
